iyal_quality_analyzer/__init__.py
iyal_quality_analyzer/quality_analyzer.py
iyal_quality_analyzer/inference_base/__init__.py
iyal_quality_analyzer/inference_base/inference.py
iyal_quality_analyzer/inference_base/inference_coll_to_stand.py
iyal_quality_analyzer/utils/__init__.py
iyal_quality_analyzer/utils/english_word_check.py
iyal_quality_analyzer/utils/special_case_check.py
iyal_quality_analyzer/utils/translator.py
iyal_quality_analyzer/utils/transliteration.py
iyal_quality_analyzer/utils/unicode_classifier.py
iyal_quality_analyzer/utils/legacy_converter/__init__.py
iyal_quality_analyzer/utils/legacy_converter/encode2utf8.py
iyal_quality_analyzer/utils/legacy_converter/legacy_converter.py
iyal_quality_analyzer/utils/logger/__init__.py
iyal_quality_analyzer/utils/logger/setup_logging.py
iyal_text_normalizer-1.1.dist-info/METADATA
iyal_text_normalizer-1.1.dist-info/WHEEL
iyal_text_normalizer-1.1.dist-info/top_level.txt
iyal_text_normalizer-1.1.dist-info/RECORD
